grafanimate/__init__.py
grafanimate/animations.py
grafanimate/commands.py
grafanimate/core.py
grafanimate/grafana-studio.js
grafanimate/grafana-util.js
grafanimate/grafana.py
grafanimate/marionette.py
grafanimate/media.py
grafanimate/model.py
grafanimate/postprocessing.py
grafanimate/scenarios.py
grafanimate/scratchpad.js
grafanimate/spool.py
grafanimate/timecontrol.py
grafanimate/timeutil.py
grafanimate/util.py
grafanimate-0.10.0.dist-info/licenses/LICENSE
grafanimate-0.10.0.dist-info/METADATA
grafanimate-0.10.0.dist-info/WHEEL
grafanimate-0.10.0.dist-info/entry_points.txt
grafanimate-0.10.0.dist-info/top_level.txt
grafanimate-0.10.0.dist-info/RECORD
