Metadata-Version: 2.4
Name: grafanimate
Version: 0.10.0
Summary: Animate timeseries data with Grafana
Author: intermittent.energy
Author-email: Andreas Motl <andreas.motl@panodata.org>, Florian Maurer <f.maurer@outlook.de>
License: AGPL 3, EUPL 1.2
Project-URL: Homepage, https://github.com/grafana-toolbox/grafanimate
Project-URL: Issues, https://github.com/grafana-toolbox/grafanimate/issues
Project-URL: Repository, https://github.com/grafana-toolbox/grafanimate
Keywords: animate,animation,automation,gif,grafana,time,video
Classifier: Development Status :: 4 - Beta
Classifier: Intended Audience :: Developers
Classifier: Intended Audience :: Education
Classifier: Intended Audience :: Information Technology
Classifier: Intended Audience :: Manufacturing
Classifier: Intended Audience :: Science/Research
Classifier: Intended Audience :: System Administrators
Classifier: Intended Audience :: Telecommunications Industry
Classifier: License :: OSI Approved :: European Union Public Licence 1.2 (EUPL 1.2)
Classifier: License :: OSI Approved :: GNU Affero General Public License v3
Classifier: Operating System :: MacOS
Classifier: Operating System :: POSIX
Classifier: Operating System :: Unix
Classifier: Programming Language :: Python
Classifier: Programming Language :: Python :: 3 :: Only
Classifier: Programming Language :: Python :: 3.9
Classifier: Programming Language :: Python :: 3.10
Classifier: Programming Language :: Python :: 3.11
Classifier: Programming Language :: Python :: 3.12
Classifier: Programming Language :: Python :: 3.13
Classifier: Topic :: Communications
Classifier: Topic :: Database
Classifier: Topic :: Internet
Classifier: Topic :: Scientific/Engineering :: Information Analysis
Classifier: Topic :: Scientific/Engineering :: Interface Engine/Protocol Translator
Classifier: Topic :: Scientific/Engineering :: Visualization
Classifier: Topic :: Software Development :: Embedded Systems
Classifier: Topic :: Software Development :: Libraries
Classifier: Topic :: System :: Archiving
Classifier: Topic :: System :: Networking :: Monitoring
Requires-Python: <3.14,>=3.9
License-File: LICENSE
Requires-Dist: datetime-interval==0.2
Requires-Dist: docopt-ng<0.10
Requires-Dist: furl<3,>=2
Requires-Dist: marionette-driver<4,>=3.4
Requires-Dist: munch>=4
Requires-Dist: python-dateutil<3,>=2.7
Requires-Dist: pytimeparse2<2,>=1.4
Requires-Dist: tqdm<5,>=4
Requires-Dist: unidecode<2,>=1
Requires-Dist: where<2,>=1
Provides-Extra: develop
Requires-Dist: mypy<1.19; extra == "develop"
Requires-Dist: poethepoet<1; extra == "develop"
Requires-Dist: pyproject-fmt<3; extra == "develop"
Requires-Dist: ruff<0.14; extra == "develop"
Requires-Dist: validate-pyproject<1; extra == "develop"
Provides-Extra: release
Requires-Dist: build<2; extra == "release"
Requires-Dist: bump2version; extra == "release"
Requires-Dist: keyring; extra == "release"
Requires-Dist: twine<7; extra == "release"
Provides-Extra: test
Requires-Dist: freezegun<2,>=1; extra == "test"
Requires-Dist: pytest<9,>=6; extra == "test"
Requires-Dist: pytest-cov<8; extra == "test"
Dynamic: license-file
